psqlsync/__init__.py
psqlsync/actions.py
psqlsync/cli.py
psqlsync/ghmoteqlync/__init__.py
psqlsync/ghmoteqlync/cli.py
psqlsync/ghmoteqlync/sync.py
psqlsync/lib.py
psqlsync-0.2.3.dist-info/LICENSE
psqlsync-0.2.3.dist-info/WHEEL
psqlsync-0.2.3.dist-info/METADATA
psqlsync-0.2.3.dist-info/entry_points.txt
psqlsync-0.2.3.dist-info/RECORD
